etc/iotronic/iotronic.conf
etc/iotronic/policy.json
etc/systemd/system/iotronic-conductor.service
etc/systemd/system/iotronic-wamp-agent.service
iotronic/__init__.py
iotronic/version.py
iotronic/api/__init__.py
iotronic/api/app.py
iotronic/api/config.py
iotronic/api/expose.py
iotronic/api/hooks.py
iotronic/api/controllers/__init__.py
iotronic/api/controllers/base.py
iotronic/api/controllers/link.py
iotronic/api/controllers/root.py
iotronic/api/controllers/v1/__init__.py
iotronic/api/controllers/v1/board.py
iotronic/api/controllers/v1/collection.py
iotronic/api/controllers/v1/enabledwebservice.py
iotronic/api/controllers/v1/fleet.py
iotronic/api/controllers/v1/location.py
iotronic/api/controllers/v1/plugin.py
iotronic/api/controllers/v1/port.py
iotronic/api/controllers/v1/request.py
iotronic/api/controllers/v1/result.py
iotronic/api/controllers/v1/service.py
iotronic/api/controllers/v1/types.py
iotronic/api/controllers/v1/utils.py
iotronic/api/controllers/v1/versions.py
iotronic/api/controllers/v1/webservice.py
iotronic/api/middleware/__init__.py
iotronic/api/middleware/auth_token.py
iotronic/api/middleware/parsable_error.py
iotronic/cmd/__init__.py
iotronic/cmd/conductor.py
iotronic/cmd/dbsync.py
iotronic/cmd/wamp_agent.py
iotronic/common/__init__.py
iotronic/common/config.py
iotronic/common/context.py
iotronic/common/designate.py
iotronic/common/exception.py
iotronic/common/hash_ring.py
iotronic/common/i18n.py
iotronic/common/keystone.py
iotronic/common/neutron.py
iotronic/common/paths.py
iotronic/common/policy.py
iotronic/common/rpc.py
iotronic/common/service.py
iotronic/common/states.py
iotronic/common/utils.py
iotronic/conductor/__init__.py
iotronic/conductor/endpoints.py
iotronic/conductor/manager.py
iotronic/conductor/provisioner.py
iotronic/conductor/rpcapi.py
iotronic/db/__init__.py
iotronic/db/api.py
iotronic/db/migration.py
iotronic/db/sqlalchemy/__init__.py
iotronic/db/sqlalchemy/alembic.ini
iotronic/db/sqlalchemy/api.py
iotronic-0.4.17.dist-info/AUTHORS
iotronic-0.4.17.dist-info/LICENSE
iotronic-0.4.17.dist-info/METADATA
iotronic-0.4.17.dist-info/WHEEL
iotronic-0.4.17.dist-info/entry_points.txt
iotronic-0.4.17.dist-info/pbr.json
iotronic-0.4.17.dist-info/top_level.txt
iotronic-0.4.17.dist-info/RECORD
