Metadata-Version: 2.1
Name: iotronic
Version: 0.4.17
Summary: IoTronic is an Internet of Things resource management service for OpenStack clouds.
Home-page: https://github.com/openstack/iotronic
Author: OpenStack
Author-email: openstack-dev@lists.openstack.org
License: UNKNOWN
Platform: UNKNOWN
Classifier: Environment :: OpenStack
Classifier: Intended Audience :: Information Technology
Classifier: Intended Audience :: System Administrators
Classifier: License :: OSI Approved :: Apache Software License
Classifier: Operating System :: POSIX :: Linux
Classifier: Programming Language :: Python
Classifier: Programming Language :: Python :: 3
Classifier: Programming Language :: Python :: 3.6
Classifier: Programming Language :: Python :: 3.7
Classifier: Programming Language :: Python :: 3.8
Requires-Dist: PyMySQL (>=0.7.6)
Requires-Dist: SQLAlchemy (!=1.1.5,!=1.1.6,!=1.1.7,!=1.1.8,>=1.0.10)
Requires-Dist: WSME (>=0.8)
Requires-Dist: autobahn (>=18.10.1)
Requires-Dist: eventlet (!=0.18.3,!=0.20.1,>=0.18.2)
Requires-Dist: keystonemiddleware (>=4.17.0)
Requires-Dist: oslo.concurrency (>=3.26.0)
Requires-Dist: oslo.config (>=5.2.0)
Requires-Dist: oslo.db (>=4.27.0)
Requires-Dist: oslo.log (>=3.36.0)
Requires-Dist: oslo.messaging (>=6.3.0)
Requires-Dist: oslo.policy (>=1.35.0)
Requires-Dist: osprofiler (>=1.5.0)
Requires-Dist: paramiko (>=2.0.0)
Requires-Dist: pbr (!=2.1.0,>=2.0.0)
Requires-Dist: pecan (!=1.0.2,!=1.0.3,!=1.0.4,!=1.2,>=1.0.0)
Requires-Dist: python-designateclient (>=2.11.0)
Requires-Dist: python-neutronclient (>=6.7.0)
